mqml/__init__.py
mqml/_version.py
mqml/conf/__init__.py
mqml/conf/telemetry.ini
mqml/instrument/__init__.py
mqml/instrument/conductresist.py
mqml/telemetry/__init__.py
mqml/telemetry/telemetry_functions.py
mqml-0.1.1.dist-info/LICENSE.rst
mqml-0.1.1.dist-info/METADATA
mqml-0.1.1.dist-info/WHEEL
mqml-0.1.1.dist-info/top_level.txt
mqml-0.1.1.dist-info/RECORD
