Metadata-Version: 2.1
Name: mqml
Version: 0.1.1
Summary: Package required to easily run measurements and analysis for the Microsoft Quantum Materials Lyngby lab. The source codes do not include Microsoft IP and are open source, so these packages could be generally useable.
Home-page: UNKNOWN
Author: Farzad Bonabi
Author-email: farzadb58@gmail.com
License: MIT
Platform: UNKNOWN
Classifier: Development Status :: 2 - Pre-Alpha
Classifier: Intended Audience :: Science/Research
Classifier: Programming Language :: Python :: 3.7
Requires-Python: >=3.7
Requires-Dist: opencensus-ext-azure
Requires-Dist: qcodes
